xai/__init__.py
xai/data/__init__.py
xai/data/census.csv
xai-0.1.0.data/data/LICENSE
xai-0.1.0.dist-info/LICENSE
xai-0.1.0.dist-info/METADATA
xai-0.1.0.dist-info/WHEEL
xai-0.1.0.dist-info/top_level.txt
xai-0.1.0.dist-info/RECORD
