Metadata-Version: 2.1
Name: xai
Version: 0.1.0
Summary: XAI - An industry-ready machine learning library that ensures explainable AI by design
Home-page: https://github.com/EthicalML/XAI
Author: Alejandro Saucedo
Author-email: a@ethical.institute
License: MIT
Keywords: xai,machine learning,deep learning,explainability,bias evaluation
Platform: UNKNOWN
Classifier: Intended Audience :: Developers
Classifier: Natural Language :: English
Classifier: Programming Language :: Python :: 3.6
Classifier: Programming Language :: Python :: 3.7
License-File: LICENSE
Requires-Dist: pandas (<1.3.4)
Requires-Dist: matplotlib (<3.4.3)
Requires-Dist: numpy (<1.21.3)
Requires-Dist: scipy (<1.7.1)
Requires-Dist: scikit-learn (<1.0.1)
Requires-Dist: python-dateutil
Requires-Dist: pytz
Requires-Dist: pyparsing
Requires-Dist: cycler
Requires-Dist: kiwisolver
Requires-Dist: six
